README.md
setup.cfg
setup.py
src/lottry/__init__.py
src/lottry/client.py
src/lottry.egg-info/PKG-INFO
src/lottry.egg-info/SOURCES.txt
src/lottry.egg-info/dependency_links.txt
src/lottry.egg-info/requires.txt
src/lottry.egg-info/top_level.txt
src/lottry/model/__init__.py
src/lottry/model/exceptions.py
src/lottry/model/movie.py
src/lottry/model/quote.py
src/lottry/model/response.py
src/lottry/querying/__init__.py
src/lottry/querying/pagination.py
src/lottry/querying/search.py
src/lottry/querying/sort.py