Metadata-Version: 2.1
Name: lottry
Version: 0.1.1
Summary: Python SDK of the lord of the rings API
Home-page: https://github.com/celerymen/lottry
Download-URL: https://github.com/celerymen/lottry/archive/v_01.tar.gz
Author: David Borsodi
Author-email: zellermester@gmail.com
License: MIT
Keywords: LoTR,SDK
Platform: UNKNOWN
Classifier: Development Status :: 3 - Alpha
Classifier: Intended Audience :: Developers
Classifier: Topic :: Software Development :: Libraries
Classifier: License :: OSI Approved :: MIT License
Classifier: Programming Language :: Python :: 3
Classifier: Programming Language :: Python :: 3.7
